Metadata-Version: 2.1
Name: pyiex
Version: 0.0.10
Summary: Python wrapper for IEX financial API
Home-page: https://github.com/wugui2020/pyIEX
Author: Wentao Lu
Author-email: wentao@wentaolu.com
License: LICENSE.txt
Keywords: python IEX
Platform: UNKNOWN
Classifier: Intended Audience :: Developers
Classifier: Topic :: Office/Business :: Financial
Classifier: Programming Language :: Python :: 2.7
Provides-Extra: test
Provides-Extra: dev
